Metadata-Version: 2.1
Name: fga
Version: 0.1
Summary: FGA consists of tools that can stack films ontop of atom slabs such that the strain in non-pseudomorphic, periodic overlayer films is minimized.
Home-page: https://github.itap.purdue.edu/GreeleyGroup/fga
Author: Kaustubh Sawant
Author-email: sawantk@purdue.edu
License: LGPLv2.1+
Platform: UNKNOWN
Requires-Python: >=3.00
License-File: LICENSE
License-File: COPYING
License-File: COPYING.LESSER
